ofxparse/__init__.py
ofxparse/mcc.py
ofxparse/ofxparse.py
ofxparse/ofxprinter.py
ofxparse/ofxutil.py
ofxparse2-0.2.2.dist-info/AUTHORS
ofxparse2-0.2.2.dist-info/LICENSE
ofxparse2-0.2.2.dist-info/METADATA
ofxparse2-0.2.2.dist-info/WHEEL
ofxparse2-0.2.2.dist-info/RECORD
