Metadata-Version: 2.3
Name: ofxparse2
Version: 0.2.2
Summary: A parser for OFX files with improved encoding detection and compatibility with malformed headers
License: MIT
Author: Pedro Schneider
Author-email: you@example.com
Requires-Python: >=3.10
Classifier: License :: OSI Approved :: MIT License
Classifier: Programming Language :: Python :: 3
Classifier: Programming Language :: Python :: 3.10
Classifier: Programming Language :: Python :: 3.11
Classifier: Programming Language :: Python :: 3.12
Classifier: Programming Language :: Python :: 3.13
Requires-Dist: beautifulsoup4 (==4.9.3)
Requires-Dist: coverage (>=7.8.0,<8.0.0)
Requires-Dist: python-coveralls (>=2.9.3,<3.0.0)
Requires-Dist: six (>=1.17.0,<2.0.0)
Project-URL: Homepage, https://github.com/pedrin-pedrada/ofxparse2
Project-URL: Repository, https://github.com/pedrin-pedrada/ofxparse2
